{"version":"0.0.0","commands":{"execute":{"id":"execute","description":"Execute a command on the sonos","pluginName":"@svrooij/sonos-cli","pluginType":"core","aliases":[],"flags":{},"args":[{"name":"device","description":"Name or uuid of player","required":true},{"name":"command","description":"command to call","required":true},{"name":"input","description":"Optional input for command"}]},"info":{"id":"info","description":"Add the supplied url to the queue","pluginName":"@svrooij/sonos-cli","pluginType":"core","aliases":[],"flags":{},"args":[{"name":"device","description":"Name or uuid of player","required":true},{"name":"info","description":"What do you want to load","required":true,"options":["attributes","media","position","queue","volume"]}]},"play":{"id":"play","description":"Add the supplied url to the queue","pluginName":"@svrooij/sonos-cli","pluginType":"core","aliases":[],"flags":{"help":{"name":"help","type":"boolean","char":"h","description":"show CLI help","allowNo":false},"skip-queue":{"name":"skip-queue","type":"boolean","allowNo":false}},"args":[{"name":"device","description":"Name or uuid of player","required":true},{"name":"url","description":"The url to play","required":true}]},"zones":{"id":"zones","description":"Do device discovery","pluginName":"@svrooij/sonos-cli","pluginType":"core","aliases":[],"flags":{"save":{"name":"save","type":"boolean","allowNo":false},"ip":{"name":"ip","type":"option","description":"Use IP instead of discovery"},"columns":{"name":"columns","type":"option","description":"only show provided columns (comma-separated)"},"sort":{"name":"sort","type":"option","description":"property to sort by (prepend '-' for descending)"},"filter":{"name":"filter","type":"option","description":"filter property by partial string matching, ex: name=foo"},"csv":{"name":"csv","type":"boolean","description":"output is csv format [alias: --output=csv]","allowNo":false},"output":{"name":"output","type":"option","description":"output in a more machine friendly format","options":["csv","json","yaml"]},"extended":{"name":"extended","type":"boolean","char":"x","description":"show extra columns","allowNo":false},"no-truncate":{"name":"no-truncate","type":"boolean","description":"do not truncate output to fit screen","allowNo":false},"no-header":{"name":"no-header","type":"boolean","description":"hide table header from output","allowNo":false}},"args":[{"name":"file"}]}}}